dwm_pracs/__init__.py
dwm_pracs/apriori/__init__.py
dwm_pracs/clustering/__init__.py
dwm_pracs/clustering/agglomerative_clustering_rishabh.py
dwm_pracs/clustering/kmeans_clustering.py
dwm_pracs/clustering/kmeans_clustering_rishabh.py
dwm_pracs/linear_regression/__init__.py
dwm_pracs/linear_regression/bhushan/__init__.py
dwm_pracs/linear_regression/bhushan/linear_reg.py
dwm_pracs/linear_regression/rishabh/__init__.py
dwm_pracs/linear_regression/rishabh/linear_regression.py
dwm_pracs/naive_bayes/__init__.py
dwm_pracs/naive_bayes/naive_bayes_pandas.py
dwm_pracs/naive_bayes/nb_csv_vinay.py
dwm_pracs/naive_bayes/nb_rishabh.py
dwm_pracs/olap/__init__.py
dwm_pracs/pagerank/__init__.py
dwm_pracs/pagerank/pagerank.py
dwm_pracs-0.0.1.6.dist-info/LICENSE
dwm_pracs-0.0.1.6.dist-info/METADATA
dwm_pracs-0.0.1.6.dist-info/WHEEL
dwm_pracs-0.0.1.6.dist-info/top_level.txt
dwm_pracs-0.0.1.6.dist-info/RECORD
