Metadata-Version: 2.1
Name: dwm-pracs
Version: 0.0.1.6
Summary: dwm-pracs
Home-page: https://github.com/bhushan-borole/dwm-pracs
Author: VRMB
License: UNKNOWN
Platform: UNKNOWN
Classifier: Programming Language :: Python :: 3
Classifier: License :: OSI Approved :: MIT License
Classifier: Operating System :: OS Independent
